Metadata-Version: 2.1
Name: match-func
Version: 0.0.1
Summary: Pattern matching as a function.
Home-page: https://github.com/Julynx/match_func
Author: Julio Cabria
Author-email: juliocabria@tutanota.com
Maintainer: Julio Cabria
Maintainer-email: juliocabria@tutanota.com
License: GPLv2
License-File: LICENSE
